pynusinov/__init__.py
pynusinov/_misc.py
pynusinov/_nusinov_euv.py
pynusinov/_nusinov_fuv.py
pynusinov/_coeffs/euvt_bands_coeffs.nc
pynusinov/_coeffs/euvt_lines_coeffs.nc
pynusinov/_coeffs/fuvt_bands_coeffs.nc
pynusinov-0.0.4b3.dist-info/licenses/LICENSE.txt
pynusinov-0.0.4b3.dist-info/METADATA
pynusinov-0.0.4b3.dist-info/WHEEL
pynusinov-0.0.4b3.dist-info/top_level.txt
pynusinov-0.0.4b3.dist-info/RECORD
