Metadata-Version: 2.4
Name: pynusinov
Version: 0.0.4b3
Summary: Python3 implementation of models of the ultraviolet radiation spectrum of the Sun.
Author-email: Anton Tatarnikov <tatarnikoffanton@yandex.ru>, Oleg Zolotov <ovz.office@gmail.com>
Project-URL: Homepage, https://github.com/klklklo/pynusinov
Keywords: Solar radiation model,EUV,FUV
Classifier: Development Status :: 4 - Beta
Classifier: Intended Audience :: Science/Research
Classifier: Programming Language :: Python :: 3
Classifier: Programming Language :: Python :: 3.7
Classifier: Programming Language :: Python :: 3.8
Classifier: Programming Language :: Python :: 3.9
Classifier: Programming Language :: Python :: 3.10
Classifier: Programming Language :: Python :: 3.11
Classifier: License :: OSI Approved :: Apache Software License
Classifier: Topic :: Scientific/Engineering :: Physics
Requires-Python: >=3.7
License-File: LICENSE.txt
Requires-Dist: importlib-resources
Requires-Dist: netcdf4
Requires-Dist: numpy
Requires-Dist: pandas
Requires-Dist: xarray
Dynamic: license-file
